iabot/__init__.py
iabot/actions.py
iabot/constants.py
iabot/handlers.py
iabot/servers.py
iaBot-0.0.7.dist-info/LICENSE
iaBot-0.0.7.dist-info/METADATA
iaBot-0.0.7.dist-info/WHEEL
iaBot-0.0.7.dist-info/top_level.txt
iaBot-0.0.7.dist-info/RECORD
