Metadata-Version: 2.1
Name: iaBot
Version: 0.0.7
Summary: A mini framework for building bots using python and can be served using different ways.
Home-page: https://github.com/satheesh1997/iaBot
Author: Satheesh Kumar
Author-email: satheesh.101097@gmail.com
License: UNKNOWN
Platform: UNKNOWN
Classifier: Programming Language :: Python :: 3
Classifier: License :: OSI Approved :: MIT License
Classifier: Operating System :: OS Independent
Requires-Python: >=3.7.0
Requires-Dist: Flask (==1.1.2)
Requires-Dist: pytest (==5.3.2)
Requires-Dist: websockets (==8.1)
